delta/__init__.py
delta/cli.py
delta/compiler.py
delta/errors.py
delta/run.py
delta/source.py
delta/backend/__init__.py
delta/backend/codegen.py
delta/backend/fx_lowering.py
delta/backend/fx_optimize.py
delta/debug/__init__.py
delta/debug/introspection.py
delta/debug/ir_printer.py
delta/debug/why_system.py
delta/frontend/__init__.py
delta/frontend/ast.py
delta/frontend/desugar.py
delta/frontend/lexer.py
delta/frontend/parser.py
delta/frontend/tokens.py
delta/ir/__init__.py
delta/ir/sir.py
delta/ir/sir_builder.py
delta/ir/sir_printer.py
delta/passes/__init__.py
delta/passes/constraint_compile.py
delta/passes/dead_gradient_elim.py
delta/passes/effect_inference.py
delta/passes/gradient_analysis.py
delta/passes/mode_check.py
delta/passes/mode_specialize.py
delta/passes/name_resolution.py
delta/passes/relaxation.py
delta/passes/role_assignment.py
delta/runtime/__init__.py
delta/runtime/cache.py
delta/runtime/context.py
delta/runtime/executor.py
delta/runtime/optimizer.py
delta/stdlib/__init__.py
delta/stdlib/constraints.py
delta/stdlib/data.py
delta/stdlib/debug.py
delta/stdlib/dist.py
delta/stdlib/nn.py
delta/stdlib/optim.py
delta/stdlib/tensor.py
delta/types/__init__.py
delta/types/checker.py
delta/types/effects.py
delta/types/inference.py
delta/types/roles.py
delta/types/types.py
delta_lang-0.1.7.dist-info/licenses/LICENSE
delta_lang-0.1.7.dist-info/METADATA
delta_lang-0.1.7.dist-info/WHEEL
delta_lang-0.1.7.dist-info/entry_points.txt
delta_lang-0.1.7.dist-info/top_level.txt
delta_lang-0.1.7.dist-info/RECORD
