Metadata-Version: 2.4
Name: delta-lang
Version: 0.1.7
Summary: A differentiable, constraint-oriented programming language that compiles to PyTorch
Author: Delta Team
License: MIT
Project-URL: Homepage, https://github.com/deltalanguage/delta
Project-URL: Documentation, https://github.com/deltalanguage/delta#readme
Project-URL: Repository, https://github.com/deltalanguage/delta
Project-URL: Issues, https://github.com/deltalanguage/delta/issues
Keywords: differentiable,programming,machine-learning,pytorch,compiler
Classifier: Development Status :: 4 - Beta
Classifier: Intended Audience :: Developers
Classifier: Intended Audience :: Science/Research
Classifier: License :: OSI Approved :: MIT License
Classifier: Programming Language :: Python :: 3
Classifier: Programming Language :: Python :: 3.10
Classifier: Programming Language :: Python :: 3.11
Classifier: Programming Language :: Python :: 3.12
Classifier: Topic :: Scientific/Engineering :: Artificial Intelligence
Classifier: Topic :: Software Development :: Compilers
Requires-Python: >=3.10
License-File: LICENSE
Requires-Dist: torch>=2.0.0
Requires-Dist: numpy>=1.24.0
Provides-Extra: dev
Requires-Dist: pytest>=7.0.0; extra == "dev"
Requires-Dist: pytest-cov>=4.0.0; extra == "dev"
Requires-Dist: mypy>=1.0.0; extra == "dev"
Requires-Dist: ruff>=0.1.0; extra == "dev"
Dynamic: license-file
